[
  {
    "id": "explore-maxim0191",
    "displayName": "洛克王国世界·探索 - maxim0191",
    "author": "Maxim0191",
    "description": "Template for Roco Kingdom",
    "catalogFolder": "Roco Kingdom",
    "fileName": "explore-maxim0191.json",
    "downloadUrl": "https://raw.githubusercontent.com/Maxim00191/GamepadMapping-CommunityProfiles/main/Roco Kingdom/explore-maxim0191.json"
  },
  {
    "id": "fight-maxim0191",
    "displayName": "洛克王国世界·战斗 - maxim0191",
    "author": "Maxim0191",
    "description": "Template for Roco Kingdom",
    "catalogFolder": "Roco Kingdom",
    "fileName": "fight-maxim0191.json",
    "downloadUrl": "https://raw.githubusercontent.com/Maxim00191/GamepadMapping-CommunityProfiles/main/Roco Kingdom/fight-maxim0191.json"
  }
]